pbitcoin/__init__.py
pbitcoin/constant.py
pbitcoin-0.0.1.dist-info/METADATA
pbitcoin-0.0.1.dist-info/WHEEL
pbitcoin-0.0.1.dist-info/top_level.txt
pbitcoin-0.0.1.dist-info/RECORD
