Metadata-Version: 2.1
Name: pbitcoin
Version: 0.0.1
Summary: Examples
Home-page: UNKNOWN
Author: Soobokjin
Author-email: thdnthdn24@gmail.com
License: BSD
Keywords: example documentation tutorial
Platform: UNKNOWN
Classifier: Development Status :: 3 - Alpha
Classifier: Topic :: Utilities
Classifier: License :: OSI Approved :: BSD License
